[
  {"symbol": "א", "polarity": "Yang", "element": "Fire", "gender": "masculine"},
  {"symbol": "ב", "polarity": "Yin", "element": "Water", "gender": "feminine"},
  {"symbol": "ג", "polarity": "Balanced", "element": "Earth", "gender": "neutral"},
  {"symbol": "ד", "polarity": "Yang", "element": "Air", "gender": "masculine"},
  {"symbol": "ה", "polarity": "Yin", "element": "Spirit", "gender": "feminine"},
  {"symbol": "ו", "polarity": "Balanced", "element": "Air", "gender": "neutral"},
  {"symbol": "ז", "polarity": "Yang", "element": "Fire", "gender": "masculine"},
  {"symbol": "ח", "polarity": "Yin", "element": "Water", "gender": "feminine"},
  {"symbol": "ט", "polarity": "Balanced", "element": "Earth", "gender": "neutral"},
  {"symbol": "י", "polarity": "Yang", "element": "Fire", "gender": "masculine"},
  {"symbol": "כ", "polarity": "Yin", "element": "Water", "gender": "feminine"},
  {"symbol": "ל", "polarity": "Balanced", "element": "Earth", "gender": "neutral"},
  {"symbol": "מ", "polarity": "Yang", "element": "Air", "gender": "masculine"},
  {"symbol": "נ", "polarity": "Yin", "element": "Spirit", "gender": "feminine"},
  {"symbol": "ס", "polarity": "Balanced", "element": "Earth", "gender": "neutral"},
  {"symbol": "ע", "polarity": "Yang", "element": "Fire", "gender": "masculine"},
  {"symbol": "פ", "polarity": "Yin", "element": "Water", "gender": "feminine"},
  {"symbol": "צ", "polarity": "Balanced", "element": "Earth", "gender": "neutral"},
  {"symbol": "ק", "polarity": "Yang", "element": "Air", "gender": "masculine"},
  {"symbol": "ר", "polarity": "Yin", "element": "Spirit", "gender": "feminine"},
  {"symbol": "ש", "polarity": "Balanced", "element": "Fire", "gender": "neutral"},
  {"symbol": "ת", "polarity": "Yang", "element": "Earth", "gender": "masculine"},
  {"symbol": "|", "polarity": "None", "element": "None", "gender": "neutral"},
  {"symbol": "·", "polarity": "None", "element": "None", "gender": "neutral"}
]